emxlib/__init__.py
emxlib/bibtex.py
emxlib/constants.py
emxlib/emx_logo.png
emxlib/protocols.conf
emxlib/utils.py
emxlib/convert/__init__.py
emxlib/convert/convert.py
emxlib/convert/dataimport.py
emxlib/protocols/__init__.py
emxlib/protocols/protocol_export.py
emxlib/tests/__init__.py
emxlib/tests/test_protocols_emx.py
emxlib/tests/test_protocols_export_particles.py
emxlib/tests/test_workflow_emx.py
emxlib/viewers/__init__.py
emxlib/viewers/emxlib_viewers.py
scipion_em_emxlib-3.0.1.dist-info/LICENSE
scipion_em_emxlib-3.0.1.dist-info/METADATA
scipion_em_emxlib-3.0.1.dist-info/WHEEL
scipion_em_emxlib-3.0.1.dist-info/entry_points.txt
scipion_em_emxlib-3.0.1.dist-info/top_level.txt
scipion_em_emxlib-3.0.1.dist-info/RECORD
