Metadata-Version: 2.1
Name: scipion-em-emxlib
Version: 3.0.1
Summary: EMX_EXPORT ready to use in scipion.
Home-page: https://github.com/scipion-em/scipion-em-emxlib
Author: I2PC
Author-email: scipion@cnb.csic.es
License: UNKNOWN
Keywords: scipion cryoem imageprocessing scipion-3.0
Platform: UNKNOWN
